zwarm/__init__.py
zwarm/orchestrator.py
zwarm/test_orchestrator_watchers.py
zwarm/cli/__init__.py
zwarm/cli/interactive.py
zwarm/cli/main.py
zwarm/cli/pilot.py
zwarm/core/__init__.py
zwarm/core/checkpoints.py
zwarm/core/compact.py
zwarm/core/config.py
zwarm/core/costs.py
zwarm/core/environment.py
zwarm/core/models.py
zwarm/core/registry.py
zwarm/core/state.py
zwarm/core/test_compact.py
zwarm/core/test_config.py
zwarm/core/test_models.py
zwarm/prompts/__init__.py
zwarm/prompts/orchestrator.py
zwarm/prompts/pilot.py
zwarm/sessions/__init__.py
zwarm/sessions/base.py
zwarm/sessions/claude.py
zwarm/sessions/manager.py
zwarm/tools/__init__.py
zwarm/tools/delegation.py
zwarm/watchers/__init__.py
zwarm/watchers/base.py
zwarm/watchers/builtin.py
zwarm/watchers/llm_watcher.py
zwarm/watchers/manager.py
zwarm/watchers/registry.py
zwarm/watchers/test_watchers.py
zwarm-3.8.0.dist-info/METADATA
zwarm-3.8.0.dist-info/WHEEL
zwarm-3.8.0.dist-info/entry_points.txt
zwarm-3.8.0.dist-info/RECORD
