Metadata-Version: 2.4
Name: zwarm
Version: 3.8.0
Summary: Multi-Agent CLI Orchestration Research Platform
Requires-Python: <3.14,>=3.13
Requires-Dist: prompt-toolkit>=3.0.52
Requires-Dist: python-dotenv>=1.0.0
Requires-Dist: pyyaml>=6.0
Requires-Dist: rich>=13.0.0
Requires-Dist: typer>=0.9.0
Requires-Dist: wbal>=0.5.8
